nanpa/__init__.py
nanpa/client.py
nanpa-1.0.1.dist-info/LICENSE
nanpa-1.0.1.dist-info/METADATA
nanpa-1.0.1.dist-info/WHEEL
nanpa-1.0.1.dist-info/top_level.txt
nanpa-1.0.1.dist-info/RECORD
