Metadata-Version: 2.1
Name: nanpa
Version: 1.0.1
Summary: North American Numbering Plan Administration (NANPA) API Client
Home-page: https://github.com/acidvegas/nanpa
Author: acidvegas
Author-email: acid.vegas@acid.vegas
Project-URL: Source Code, https://github.com/acidvegas/nanpa
Classifier: Development Status :: 4 - Beta
Classifier: Intended Audience :: Developers
Classifier: License :: OSI Approved :: MIT License
Classifier: Operating System :: OS Independent
Classifier: Programming Language :: Python :: 3
Classifier: Programming Language :: Python :: 3.6
Classifier: Programming Language :: Python :: 3.7
Classifier: Programming Language :: Python :: 3.8
Classifier: Programming Language :: Python :: 3.9
Classifier: Programming Language :: Python :: 3.10
Classifier: Programming Language :: Python :: 3.11
Classifier: Topic :: Software Development :: Libraries :: Python Modules
Classifier: Topic :: Communications :: Telephony
Requires-Python: >=3.6
License-File: LICENSE
